src/__init__.py
src/dwr.cpython-312-x86_64-linux-gnu.so
dwrandomizer_wrapper-0.3.0.dist-info/METADATA
dwrandomizer_wrapper-0.3.0.dist-info/WHEEL
dwrandomizer_wrapper-0.3.0.dist-info/RECORD
