Metadata-Version: 2.4
Name: dwrandomizer-wrapper
Version: 0.3.0
Summary: A Cython wrapper for the C based Dragon Warrior Randomizer, for use with Archipelago
Author-email: Peter Ghobrial <peter_ghob@yahoo.ca>
License-Expression: MIT
Classifier: Operating System :: OS Independent
Classifier: Programming Language :: Python :: 3
Requires-Python: >=3.9
